soda/data_sources/snowflake_contract_data_source.py
soda/data_sources/snowflake_data_source.py
soda_core_snowflake-3.5.6.dist-info/LICENSE
soda_core_snowflake-3.5.6.dist-info/METADATA
soda_core_snowflake-3.5.6.dist-info/WHEEL
soda_core_snowflake-3.5.6.dist-info/top_level.txt
soda_core_snowflake-3.5.6.dist-info/RECORD
