Metadata-Version: 2.1
Name: soda-core-snowflake
Version: 3.5.6
License-File: LICENSE
Requires-Dist: soda-core==3.5.6
Requires-Dist: snowflake-connector-python~=3.0
